diskcache/__init__.py
diskcache/cli.py
diskcache/core.py
diskcache/djangocache.py
diskcache/fanout.py
diskcache/persistent.py
diskcache/recipes.py
diskcache2-1.0.0.dist-info/METADATA
diskcache2-1.0.0.dist-info/WHEEL
diskcache2-1.0.0.dist-info/entry_points.txt
diskcache2-1.0.0.dist-info/licenses/LICENSE
diskcache2-1.0.0.dist-info/RECORD
