Metadata-Version: 2.1
Name: diskcache2
Version: 1.0.0
Summary: Disk Cache -- Disk and file backed persistent cache.
Author-Email: Grant Jenks <contact@grantjenks.com>
Maintainer-Email: Muspi Merol <me@promplate.dev>
License: Apache 2.0
Classifier: Development Status :: 5 - Production/Stable
Classifier: Intended Audience :: Developers
Classifier: License :: OSI Approved :: Apache Software License
Classifier: Natural Language :: English
Classifier: Programming Language :: Python
Classifier: Programming Language :: Python :: 3
Classifier: Programming Language :: Python :: 3.9
Classifier: Programming Language :: Python :: 3.10
Classifier: Programming Language :: Python :: 3.11
Classifier: Programming Language :: Python :: 3.12
Classifier: Programming Language :: Python :: 3.13
Classifier: Programming Language :: Python :: Implementation :: CPython
Project-URL: Homepage, http://www.grantjenks.com/docs/diskcache/
Project-URL: Documentation, http://www.grantjenks.com/docs/diskcache/
Project-URL: Funding, https://gum.co/diskcache
Project-URL: Source, https://github.com/grantjenks/python-diskcache
Project-URL: Tracker, https://github.com/grantjenks/python-diskcache/issues
Requires-Python: ~=3.10
